MANIFEST.in
README.rst
setup.py
termite/__init__.py
termite/cmdline.py
termite/parser.py
termite/server.py
termite/utils.py
termite.egg-info/PKG-INFO
termite.egg-info/SOURCES.txt
termite.egg-info/dependency_links.txt
termite.egg-info/entry_points.txt
termite.egg-info/requires.txt
termite.egg-info/top_level.txt