Metadata-Version: 1.1
Name: termite
Version: 0.0.1
Summary: Automates your build process
Home-page: http://jlesquembre.github.io/termite/
Author: Jose Luis Lafuente
Author-email: jlesquembre@gmail.com
License: GNU General Public License v3 (GPLv3)
Keywords: automation,web
Platform: UNKNOWN
Classifier: Development Status :: 3 - Alpha
Classifier: Topic :: Utilities
Classifier: Intended Audience :: Developers
Classifier: License :: OSI Approved :: GNU General Public License v3 (GPLv3)
Classifier: Operating System :: OS Independent
Classifier: Programming Language :: Python
Classifier: Programming Language :: Python :: 3.3
